ome_model/__init__.py
ome_model/experimental.py
ome_model-6.4.0.dist-info/LICENSE.md
ome_model-6.4.0.dist-info/METADATA
ome_model-6.4.0.dist-info/WHEEL
ome_model-6.4.0.dist-info/top_level.txt
ome_model-6.4.0.dist-info/RECORD
